verify_firebase_token/__init__.py
verify_firebase_token-0.1.3.dist-info/METADATA
verify_firebase_token-0.1.3.dist-info/WHEEL
verify_firebase_token-0.1.3.dist-info/RECORD
