Metadata-Version: 2.1
Name: verify-firebase-token
Version: 0.1.3
Summary: 
Author: Jeremy Berman
Author-email: jerber@sas.upenn.edu
Requires-Python: >=3.10,<4.0
Classifier: Programming Language :: Python :: 3
Classifier: Programming Language :: Python :: 3.10
Classifier: Programming Language :: Python :: 3.11
Classifier: Programming Language :: Python :: 3.12
Requires-Dist: cryptography (>=42.0,<43.0)
Requires-Dist: pyjwt (>=2.8,<3.0)
Requires-Dist: requests (>=2.31,<3.0)
